<?xml version="1.0" encoding="UTF-8"?>
<metadata xml:lang="en"><Esri><CreaDate>20210720</CreaDate><CreaTime>04043000</CreaTime><ArcGISFormat>1.0</ArcGISFormat><SyncOnce>TRUE</SyncOnce><DataProperties><lineage><Process ToolSource="c:\program files (x86)\arcgis\desktop10.6\ArcToolbox\Toolboxes\Data Management Tools.tbx\CalculateField" Date="20210720" Time="040430">CalculateField OSDS_MASTER_RiskFactors_v6_NOKAITLINtest RFish_rank 4 VB #</Process><Process ToolSource="c:\program files (x86)\arcgis\desktop10.6\ArcToolbox\Toolboxes\Data Management Tools.tbx\CalculateField" Date="20210720" Time="040439">CalculateField OSDS_MASTER_RiskFactors_v6_NOKAITLINtest Coral_rank 4 VB #</Process></lineage></DataProperties></Esri></metadata>
